{"name":"Foss project","tagline":"project for foss class","body":"This is a starter project for our FOSS class in college under our undergraduate course in computer science.  \r\nOur IRC channel is #foss_class on [freenode](https://webchat.freeenode.net).  \r\nYou can join our mailing list foss_class@googlegroups.com  \r\nFor further details contact  \r\n[Nareesh Devaraj](https://github.com/nareesh/foss_project/)  \r\n[Sai Hemanth](https://github.com/)\r\n\r\nOur project mentor is [Mr. Dayanand V](https://github.com/dayanandv)","google":"","note":"Don't delete this file! It's used internally to help with page regeneration."}